LICENSE
README.md
setup.py
example_package_qianzelinthu/__init__.py
example_package_qianzelinthu/example.py
example_package_qianzelinthu.egg-info/PKG-INFO
example_package_qianzelinthu.egg-info/SOURCES.txt
example_package_qianzelinthu.egg-info/dependency_links.txt
example_package_qianzelinthu.egg-info/top_level.txt