Metadata-Version: 2.1
Name: example-package-qianzelinthu
Version: 0.1.0
Summary: testttt
Home-page: https://github.com/ZelinQian/SPIDER
Author: Zelin Qian
Author-email: qzl22@mails.tsinghua.edu.cn
License: MIT
Platform: UNKNOWN
Requires-Python: >=3.6
